{"data_mtime": 1585836164, "dep_lines": [1, 2, 1, 1, 1], "dep_prios": [10, 5, 5, 30, 30], "dependencies": ["pprint", "datetime", "builtins", "abc", "typing"], "hash": "24955aecb43fcf56dcf733c78867d46bda34bc5bf30f7fa32e00957906fc2502", "id": "backtradermql5.adapter", "ignore_all": false, "interface_hash": "ad2fd7f46fbb99e29939a557a22c53e5b77ee5bb1f106237b0f48ca5b30e2fed", "mtime": 1582555009, "options": {"allow_redefinition": false, "allow_untyped_globals": false, "always_false": [], "always_true": [], "bazel": false, "check_untyped_defs": false, "disallow_any_decorated": false, "disallow_any_explicit": false, "disallow_any_expr": false, "disallow_any_generics": false, "disallow_any_unimported": false, "disallow_incomplete_defs": false, "disallow_subclassing_any": false, "disallow_untyped_calls": false, "disallow_untyped_decorators": false, "disallow_untyped_defs": false, "follow_imports": "silent", "follow_imports_for_stubs": false, "ignore_errors": false, "ignore_missing_imports": true, "implicit_reexport": true, "local_partial_types": false, "mypyc": false, "no_implicit_optional": false, "platform": "linux", "plugins": [], "show_none_errors": true, "strict_equality": false, "strict_optional": true, "strict_optional_whitelist": null, "warn_no_return": true, "warn_return_any": false, "warn_unreachable": false, "warn_unused_ignores": false}, "path": "/home/awahyudi/Projects/backtrader/Backtrader-MQL5-API/backtradermql5/adapter.py", "plugin_data": null, "size": 729, "suppressed": [], "version_id": "0.770"}